Workbook

Sheet Raw_GDP
A1: Year | B1: GDP_Current_LakhCr | C1: GDP_Constant_LakhCr | D1: Agriculture_Share_% | E1: Industry_Share_% | F1: Services_Share_% | G1: Real_Growth_%
A2: 2014-15 | B2: 124.68 | C2: 105.28 | D2: 17.76 | E2: 29.65 | F2: 52.59 | G2: 7.41
A3: 2015-16 | B3: 135.76 | C3: 113.69 | D3: 17.5 | E3: 29 | F3: 53.5 | G3: 8
A4: 2016-17 | B4: 153.92 | C4: 123.08 | D4: 17.95 | E4: 29.29 | F4: 52.76 | G4: 8.26
A5: 2017-18 | B5: 170.9 | C5: 131.45 | D5: 17.12 | E5: 27.84 | F5: 55.04 | G5: 6.8
A6: 2018-19 | B6: 188.99 | C6: 139.93 | D6: 16.45 | E6: 27.53 | F6: 56.02 | G6: 6.45
A7: 2019-20 | B7: 201.04 | C7: 145.35 | D7: 17.31 | E7: 26.17 | F7: 56.52 | G7: 3.87
A8: 2020-21 | B8: 198.54 | C8: 136.95 | D8: 20.2 | E8: 25.49 | F8: 54.31 | G8: -5.78
A9: 2021-22 | B9: 235.97 | C9: 150.22 | D9: 18.18 | E9: 27.3 | F9: 54.52 | G9: 9.69
A10: 2022-23 | B10: 268.9 | C10: 161.65 | D10: 18.14 | E10: 26.85 | F10: 55.01 | G10: 7
A11: 2023-24 | B11: 301.23 | C11: 176.51 | D11: 17.69 | E11: 25.75 | F11: 56.56 | G11: 8.2
A12: 2024-25 | B12: 330.68 | C12: 187.97 | D12: 17.94 | E12: 27.13 | F12: 54.93 | G12: 6.49
A13: 2025-26 | B13: 345.47 | C13: 201.9 | D13: 18 | E13: 26.4 | F13: 55.6 | G13: 7.6

Sheet Raw_Inflation
A1: Year | B1: CPI_Avg | C1: WPI_Avg | D1: CPI_Inflation_% | E1: WPI_Inflation_%
A2: 2014-15 | B2: 119.8 | C2: 113.9 | D2: 5.85 | E2: 1.2
A3: 2015-16 | B3: 125.7 | C3: 109.7 | D3: 4.91 | E3: -3.7
A4: 2016-17 | B4: 131.4 | C4: 111.6 | D4: 4.52 | E4: 1.7
A5: 2017-18 | B5: 136.1 | C5: 114.9 | D5: 3.59 | E5: 3
A6: 2018-19 | B6: 140.8 | C6: 119.8 | D6: 3.41 | E6: 4.3
A7: 2019-20 | B7: 147.5 | C7: 121.8 | D7: 4.77 | E7: 1.7
A8: 2020-21 | B8: 156.7 | C8: 123.4 | D8: 6.16 | E8: -0.1
A9: 2021-22 | B9: 165.2 | C9: 139.4 | D9: 5.51 | E9: 13
A10: 2022-23 | B10: 176.3 | C10: 152.5 | D10: 6.7 | E10: 9.45
A11: 2023-24 | B11: 185.7 | C11: 151.4 | D11: 5.4 | E11: 0.7
A12: 2024-25 | B12: 194.1 | C12: 154.9 | D12: 4.6 | E12: 2.3

Sheet Raw_Unemployment
A1: Year | B1: Unemployment_Overall_% | C1: Unemployment_Rural_% | D1: Unemployment_Urban_%
A2: 2013-14 | B2: 4.9 | C2: 4.4 | D2: 4.9
A3: 2014-15 | B3: 3.8 | C3: 3.4 | D3: 5
A4: 2015-16 | B4: 5 | C4: 5.1 | D4: 4.9
A5: 2016-17 | B5: 5.4 | C5: 5.1 | D5: 5.7
A6: 2017-18 | B6: 6.1 | C6: 5.3 | D6: 7.7
A7: 2018-19 | B7: 5.8 | C7: 5 | D7: 7.7
A8: 2019-20 | B8: 4.8 | C8: 3.9 | D8: 7.3
A9: 2020-21 | B9: 4.2 | C9: 3.3 | D9: 6.7
A10: 2021-22 | B10: 4.1 | C10: 3.2 | D10: 6.3
A11: 2022-23 | B11: 3.2 | C11: 2.4 | D11: 5.4
A12: 2023-24 | B12: 3.2 | C12: 2.5 | D12: 5.1
A13: 2024-25 | B13: 4.9 | C13: ~ 4.1 | D13: ~ 6.9

Sheet Raw_FDI
A1: Year | B1: FDI_Total_USD_Bn | C1: FDI_Equity_USD_Bn | D1: Top_Sector | E1: FDI_Change_%
A2: 2013-14 | B2: 36.05 | C2: 24.3 | D2: Services | E2: — (Baseline)
A3: 2014-15 | B3: 45.15 | C3: 30.93 | D3: Services | E3: 0.25
A4: 2015-16 | B4: 55.56 | C4: 40 | D4: Services | E4: 0.23
A5: 2016-17 | B5: 60.22 | C5: 43.48 | D5: Services | E5: 0.08
A6: 2017-18 | B6: 60.97 | C6: 44.86 | D6: Services | E6: 0.01
A7: 2018-19 | B7: 62 | C7: 44.37 | D7: Services | E7: 0.02
A8: 2019-20 | B8: 74.39 | C8: 49.98 | D8: Services | E8: 0.2
A9: 2020-21 | B9: 81.97 | C9: 59.64 | D9: Computer Software & Hardware | E9: 0.1
A10: 2021-22 | B10: 84.84 | C10: 58.77 | D10: Computer Software & Hardware | E10: 0.03
A11: 2022-23 | B11: 71.36 | C11: 46.03 | D11: Computer Software & Hardware | E11: -0.16
A12: 2023-24 | B12: 71.28 | C12: 44.42 | D12: Computer Software & Hardware | E12: ~0%
A13: 2024-25 | B13: 81.04 | C13: 50.02 | D13: Services | E13: 0.14

Sheet Raw_Trade
A1: Year | B1: Merch_Exports_USD_Bn | C1: Merch_Imports_USD_Bn | D1: Merch_Trade_Balance_USD_Bn | E1: Services_Exports_USD_Bn | F1: Services_Imports_USD_Bn | G1: Overall_Trade_Balance_USD_Bn | H1: Services Trade Balance
A2: 2015-16 | B2: 261.1 | C2: 381 | D2: -119.9 | E2: 155.6 | F2: 88.2 | G2: -52.5 | H2: 67.4
A3: 2016-17 | B3: 275.9 | C3: 392.6 | D3: -116.7 | E3: 163.8 | F3: 92 | G3: -44.9 | H3: 71.8
A4: 2017-18 | B4: 303.5 | C4: 465.6 | D4: -162.1 | E4: 185.4 | F4: 111.7 | G4: -88.4 | H4: 73.7
A5: 2018-19 | B5: 331 | C5: 514.1 | D5: -183.1 | E5: 207.1 | F5: 123.1 | G5: -99.1 | H5: 84
A6: 2019-20 | B6: 314.3 | C6: 467.2 | D6: -152.9 | E6: 213.9 | F6: 133.3 | G6: -72.3 | H6: 80.6
A7: 2020-21 | B7: 291.8 | C7: 394.4 | D7: -102.6 | E7: 178 | F7: 106.7 | G7: -31.3 | H7: 71.3
A8: 2021-22 | B8: 422 | C8: 612 | D8: -190 | E8: 254.5 | F8: 147.4 | G8: -82.9 | H8: 107.1
A9: 2022-23 | B9: 451.1 | C9: 714.2 | D9: -263.1 | E9: 322.7 | F9: 158.3 | G9: -98.7 | H9: 164.4
A10: 2023-24 | B10: 437.1 | C10: 678.2 | D10: -241.1 | E10: 341.1 | F10: 178.3 | G10: -78.3 | H10: 162.8
A11: 2024-25 | B11: 437.4 | C11: 720.2 | D11: -282.8 | E11: 387.5 | F11: 198.7 | G11: -94 | H11: 188.8

Sheet Raw_PerCapita
A1: Year | B1: PerCapita_NNI_Rs | C1: PerCapita_Growth_%
A2: 2015-16 | B2: 94797 | C2: 0.096
A3: 2016-17 | B3: 104880 | C3: 0.106
A4: 2017-18 | B4: 115293 | C4: 0.099
A5: 2018-19 | B5: 126521 | C5: 0.097
A6: 2019-20 | B6: 134226 | C6: 0.061
A7: 2020-21 | B7: 127065 | C7: -0.053
A8: 2021-22 | B8: 148524 | C8: 0.169
A9: 2022-23 | B9: 169496 | C9: 0.141
A10: 2023-24 | B10: 188892 | C10: 0.114
A11: 2024-25 | B11: 209179 | C11: 0.107

Sheet Master_Data
A1: Year | B1: GDP_Current_LakhCr | C1: GDP_Constant_LakhCr | D1: Agriculture_Share_% | E1: Industry_Share_% | F1: Services_Share_% | G1: Real_GDP_Growth_% | H1: CPI_Inflation_% | I1: WPI_Inflation_% | J1: Unemployment_Overall_% | K1: Unemployment_Rural_% | L1: Unemployment_Urban_% | M1: FDI_Total_USD_Bn | N1: FDI_Equity_USD_Bn | O1: Merch_Exports_USD_Bn | P1: Merch_Imports_USD_Bn | Q1: Merch_Trade_Balance_USD_Bn | R1: Services_Exports_USD_Bn | S1: Services_Imports_USD_Bn | T1: Overall_Trade_Balance_USD_Bn | U1: PerCapita_NNI_Rs | V1: PerCapita_Growth_%
A2: 2015-16 | B2: =VLOOKUP($A2, Raw_GDP!$A$2:$G$13, 2, FALSE) -> 135.76 | C2: =VLOOKUP($A2, Raw_GDP!$A$2:$G$13, 3, FALSE) -> 113.69 | D2: =VLOOKUP(A2, Raw_GDP!A2:G13, 4, FALSE) -> 17.5 | E2: =VLOOKUP(A2, Raw_GDP!A2:G13, 5, FALSE) -> 29 | F2: =VLOOKUP($A2, Raw_GDP!$A$2:$G$13, 6, FALSE) -> 53.5 | G2: =VLOOKUP($A2, Raw_GDP!$A$2:$G$13, 7, FALSE) -> 8 | H2: =VLOOKUP($A2, Raw_Inflation!$A$2:$E$12, 4, FALSE) -> 4.91 | I2: =VLOOKUP($A2, Raw_Inflation!$A$2:$E$12, 5, FALSE) -> -3.7 | J2: =VLOOKUP($A2, Raw_Unemployment!$A$2:$D$14, 2, FALSE) -> 5 | K2: =VLOOKUP($A2, Raw_Unemployment!$A$2:$D$14, 3, FALSE) -> 5.1 | L2: =VLOOKUP($A2, Raw_Unemployment!$A$2:$D$14, 4, FALSE) -> 4.9 | M2: =VLOOKUP($A2, Raw_FDI!$A$2:$E$14, 2, FALSE) -> 55.56 | N2: =VLOOKUP($A2, Raw_FDI!$A$2:$E$14, 3, FALSE) -> 40 | O2: =VLOOKUP($A2, Raw_Trade!$A$2:$G$12, 2, FALSE) -> 261.1 | P2: =VLOOKUP($A2, Raw_Trade!$A$2:$G$12, 3, FALSE) -> 381 | Q2: =VLOOKUP($A2, Raw_Trade!$A$2:$G$12, 4, FALSE) -> -119.9 | R2: =VLOOKUP($A2, Raw_Trade!$A$2:$G$12, 5, FALSE) -> 155.6 | S2: =VLOOKUP($A2, Raw_Trade!$A$2:$G$12, 6, FALSE) -> 88.2 | T2: =VLOOKUP($A2, Raw_Trade!$A$2:$G$12, 7, FALSE) -> -52.5 | U2: =VLOOKUP($A2, Raw_PerCapita!$A$2:$C$12, 2, FALSE) -> 94797 | V2: =VLOOKUP($A2, Raw_PerCapita!$A$2:$C$12, 3, FALSE) -> 0.096
A3: 2016-17 | B3: =VLOOKUP($A3, Raw_GDP!$A$2:$G$13, 2, FALSE) -> 153.92 | C3: =VLOOKUP($A3, Raw_GDP!$A$2:$G$13, 3, FALSE) -> 123.08 | D3: =VLOOKUP(A3, Raw_GDP!A3:G14, 4, FALSE) -> 17.95 | E3: =VLOOKUP(A3, Raw_GDP!A3:G14, 5, FALSE) -> 29.29 | F3: =VLOOKUP($A3, Raw_GDP!$A$2:$G$13, 6, FALSE) -> 52.76 | G3: =VLOOKUP($A3, Raw_GDP!$A$2:$G$13, 7, FALSE) -> 8.26 | H3: =VLOOKUP($A3, Raw_Inflation!$A$2:$E$12, 4, FALSE) -> 4.52 | I3: =VLOOKUP($A3, Raw_Inflation!$A$2:$E$12, 5, FALSE) -> 1.7 | J3: =VLOOKUP($A3, Raw_Unemployment!$A$2:$D$14, 2, FALSE) -> 5.4 | K3: =VLOOKUP($A3, Raw_Unemployment!$A$2:$D$14, 3, FALSE) -> 5.1 | L3: =VLOOKUP($A3, Raw_Unemployment!$A$2:$D$14, 4, FALSE) -> 5.7 | M3: =VLOOKUP($A3, Raw_FDI!$A$2:$E$14, 2, FALSE) -> 60.22 | N3: =VLOOKUP($A3, Raw_FDI!$A$2:$E$14, 3, FALSE) -> 43.48 | O3: =VLOOKUP($A3, Raw_Trade!$A$2:$G$12, 2, FALSE) -> 275.9 | P3: =VLOOKUP($A3, Raw_Trade!$A$2:$G$12, 3, FALSE) -> 392.6 | Q3: =VLOOKUP($A3, Raw_Trade!$A$2:$G$12, 4, FALSE) -> -116.7 | R3: =VLOOKUP($A3, Raw_Trade!$A$2:$G$12, 5, FALSE) -> 163.8 | S3: =VLOOKUP($A3, Raw_Trade!$A$2:$G$12, 6, FALSE) -> 92 | T3: =VLOOKUP($A3, Raw_Trade!$A$2:$G$12, 7, FALSE) -> -44.9 | U3: =VLOOKUP($A3, Raw_PerCapita!$A$2:$C$12, 2, FALSE) -> 104880 | V3: =VLOOKUP($A3, Raw_PerCapita!$A$2:$C$12, 3, FALSE) -> 0.106
A4: 2017-18 | B4: =VLOOKUP($A4, Raw_GDP!$A$2:$G$13, 2, FALSE) -> 170.9 | C4: =VLOOKUP($A4, Raw_GDP!$A$2:$G$13, 3, FALSE) -> 131.45 | D4: =VLOOKUP(A4, Raw_GDP!A4:G15, 4, FALSE) -> 17.12 | E4: =VLOOKUP(A4, Raw_GDP!A4:G15, 5, FALSE) -> 27.84 | F4: =VLOOKUP($A4, Raw_GDP!$A$2:$G$13, 6, FALSE) -> 55.04 | G4: =VLOOKUP($A4, Raw_GDP!$A$2:$G$13, 7, FALSE) -> 6.8 | H4: =VLOOKUP($A4, Raw_Inflation!$A$2:$E$12, 4, FALSE) -> 3.59 | I4: =VLOOKUP($A4, Raw_Inflation!$A$2:$E$12, 5, FALSE) -> 3 | J4: =VLOOKUP($A4, Raw_Unemployment!$A$2:$D$14, 2, FALSE) -> 6.1 | K4: =VLOOKUP($A4, Raw_Unemployment!$A$2:$D$14, 3, FALSE) -> 5.3 | L4: =VLOOKUP($A4, Raw_Unemployment!$A$2:$D$14, 4, FALSE) -> 7.7 | M4: =VLOOKUP($A4, Raw_FDI!$A$2:$E$14, 2, FALSE) -> 60.97 | N4: =VLOOKUP($A4, Raw_FDI!$A$2:$E$14, 3, FALSE) -> 44.86 | O4: =VLOOKUP($A4, Raw_Trade!$A$2:$G$12, 2, FALSE) -> 303.5 | P4: =VLOOKUP($A4, Raw_Trade!$A$2:$G$12, 3, FALSE) -> 465.6 | Q4: =VLOOKUP($A4, Raw_Trade!$A$2:$G$12, 4, FALSE) -> -162.1 | R4: =VLOOKUP($A4, Raw_Trade!$A$2:$G$12, 5, FALSE) -> 185.4 | S4: =VLOOKUP($A4, Raw_Trade!$A$2:$G$12, 6, FALSE) -> 111.7 | T4: =VLOOKUP($A4, Raw_Trade!$A$2:$G$12, 7, FALSE) -> -88.4 | U4: =VLOOKUP($A4, Raw_PerCapita!$A$2:$C$12, 2, FALSE) -> 115293 | V4: =VLOOKUP($A4, Raw_PerCapita!$A$2:$C$12, 3, FALSE) -> 0.099
A5: 2018-19 | B5: =VLOOKUP($A5, Raw_GDP!$A$2:$G$13, 2, FALSE) -> 188.99 | C5: =VLOOKUP($A5, Raw_GDP!$A$2:$G$13, 3, FALSE) -> 139.93 | D5: =VLOOKUP(A5, Raw_GDP!A5:G16, 4, FALSE) -> 16.45 | E5: =VLOOKUP(A5, Raw_GDP!A5:G16, 5, FALSE) -> 27.53 | F5: =VLOOKUP($A5, Raw_GDP!$A$2:$G$13, 6, FALSE) -> 56.02 | G5: =VLOOKUP($A5, Raw_GDP!$A$2:$G$13, 7, FALSE) -> 6.45 | H5: =VLOOKUP($A5, Raw_Inflation!$A$2:$E$12, 4, FALSE) -> 3.41 | I5: =VLOOKUP($A5, Raw_Inflation!$A$2:$E$12, 5, FALSE) -> 4.3 | J5: =VLOOKUP($A5, Raw_Unemployment!$A$2:$D$14, 2, FALSE) -> 5.8 | K5: =VLOOKUP($A5, Raw_Unemployment!$A$2:$D$14, 3, FALSE) -> 5 | L5: =VLOOKUP($A5, Raw_Unemployment!$A$2:$D$14, 4, FALSE) -> 7.7 | M5: =VLOOKUP($A5, Raw_FDI!$A$2:$E$14, 2, FALSE) -> 62 | N5: =VLOOKUP($A5, Raw_FDI!$A$2:$E$14, 3, FALSE) -> 44.37 | O5: =VLOOKUP($A5, Raw_Trade!$A$2:$G$12, 2, FALSE) -> 331 | P5: =VLOOKUP($A5, Raw_Trade!$A$2:$G$12, 3, FALSE) -> 514.1 | Q5: =VLOOKUP($A5, Raw_Trade!$A$2:$G$12, 4, FALSE) -> -183.1 | R5: =VLOOKUP($A5, Raw_Trade!$A$2:$G$12, 5, FALSE) -> 207.1 | S5: =VLOOKUP($A5, Raw_Trade!$A$2:$G$12, 6, FALSE) -> 123.1 | T5: =VLOOKUP($A5, Raw_Trade!$A$2:$G$12, 7, FALSE) -> -99.1 | U5: =VLOOKUP($A5, Raw_PerCapita!$A$2:$C$12, 2, FALSE) -> 126521 | V5: =VLOOKUP($A5, Raw_PerCapita!$A$2:$C$12, 3, FALSE) -> 0.097
A6: 2019-20 | B6: =VLOOKUP($A6, Raw_GDP!$A$2:$G$13, 2, FALSE) -> 201.04 | C6: =VLOOKUP($A6, Raw_GDP!$A$2:$G$13, 3, FALSE) -> 145.35 | D6: =VLOOKUP(A6, Raw_GDP!A6:G17, 4, FALSE) -> 17.31 | E6: =VLOOKUP(A6, Raw_GDP!A6:G17, 5, FALSE) -> 26.17 | F6: =VLOOKUP($A6, Raw_GDP!$A$2:$G$13, 6, FALSE) -> 56.52 | G6: =VLOOKUP($A6, Raw_GDP!$A$2:$G$13, 7, FALSE) -> 3.87 | H6: =VLOOKUP($A6, Raw_Inflation!$A$2:$E$12, 4, FALSE) -> 4.77 | I6: =VLOOKUP($A6, Raw_Inflation!$A$2:$E$12, 5, FALSE) -> 1.7 | J6: =VLOOKUP($A6, Raw_Unemployment!$A$2:$D$14, 2, FALSE) -> 4.8 | K6: =VLOOKUP($A6, Raw_Unemployment!$A$2:$D$14, 3, FALSE) -> 3.9 | L6: =VLOOKUP($A6, Raw_Unemployment!$A$2:$D$14, 4, FALSE) -> 7.3 | M6: =VLOOKUP($A6, Raw_FDI!$A$2:$E$14, 2, FALSE) -> 74.39 | N6: =VLOOKUP($A6, Raw_FDI!$A$2:$E$14, 3, FALSE) -> 49.98 | O6: =VLOOKUP($A6, Raw_Trade!$A$2:$G$12, 2, FALSE) -> 314.3 | P6: =VLOOKUP($A6, Raw_Trade!$A$2:$G$12, 3, FALSE) -> 467.2 | Q6: =VLOOKUP($A6, Raw_Trade!$A$2:$G$12, 4, FALSE) -> -152.9 | R6: =VLOOKUP($A6, Raw_Trade!$A$2:$G$12, 5, FALSE) -> 213.9 | S6: =VLOOKUP($A6, Raw_Trade!$A$2:$G$12, 6, FALSE) -> 133.3 | T6: =VLOOKUP($A6, Raw_Trade!$A$2:$G$12, 7, FALSE) -> -72.3 | U6: =VLOOKUP($A6, Raw_PerCapita!$A$2:$C$12, 2, FALSE) -> 134226 | V6: =VLOOKUP($A6, Raw_PerCapita!$A$2:$C$12, 3, FALSE) -> 0.061
A7: 2020-21 | B7: =VLOOKUP($A7, Raw_GDP!$A$2:$G$13, 2, FALSE) -> 198.54 | C7: =VLOOKUP($A7, Raw_GDP!$A$2:$G$13, 3, FALSE) -> 136.95 | D7: =VLOOKUP(A7, Raw_GDP!A7:G18, 4, FALSE) -> 20.2 | E7: =VLOOKUP(A7, Raw_GDP!A7:G18, 5, FALSE) -> 25.49 | F7: =VLOOKUP($A7, Raw_GDP!$A$2:$G$13, 6, FALSE) -> 54.31 | G7: =VLOOKUP($A7, Raw_GDP!$A$2:$G$13, 7, FALSE) -> -5.78 | H7: =VLOOKUP($A7, Raw_Inflation!$A$2:$E$12, 4, FALSE) -> 6.16 | I7: =VLOOKUP($A7, Raw_Inflation!$A$2:$E$12, 5, FALSE) -> -0.1 | J7: =VLOOKUP($A7, Raw_Unemployment!$A$2:$D$14, 2, FALSE) -> 4.2 | K7: =VLOOKUP($A7, Raw_Unemployment!$A$2:$D$14, 3, FALSE) -> 3.3 | L7: =VLOOKUP($A7, Raw_Unemployment!$A$2:$D$14, 4, FALSE) -> 6.7 | M7: =VLOOKUP($A7, Raw_FDI!$A$2:$E$14, 2, FALSE) -> 81.97 | N7: =VLOOKUP($A7, Raw_FDI!$A$2:$E$14, 3, FALSE) -> 59.64 | O7: =VLOOKUP($A7, Raw_Trade!$A$2:$G$12, 2, FALSE) -> 291.8 | P7: =VLOOKUP($A7, Raw_Trade!$A$2:$G$12, 3, FALSE) -> 394.4 | Q7: =VLOOKUP($A7, Raw_Trade!$A$2:$G$12, 4, FALSE) -> -102.6 | R7: =VLOOKUP($A7, Raw_Trade!$A$2:$G$12, 5, FALSE) -> 178 | S7: =VLOOKUP($A7, Raw_Trade!$A$2:$G$12, 6, FALSE) -> 106.7 | T7: =VLOOKUP($A7, Raw_Trade!$A$2:$G$12, 7, FALSE) -> -31.3 | U7: =VLOOKUP($A7, Raw_PerCapita!$A$2:$C$12, 2, FALSE) -> 127065 | V7: =VLOOKUP($A7, Raw_PerCapita!$A$2:$C$12, 3, FALSE) -> -0.053
A8: 2021-22 | B8: =VLOOKUP($A8, Raw_GDP!$A$2:$G$13, 2, FALSE) -> 235.97 | C8: =VLOOKUP($A8, Raw_GDP!$A$2:$G$13, 3, FALSE) -> 150.22 | D8: =VLOOKUP(A8, Raw_GDP!A8:G19, 4, FALSE) -> 18.18 | E8: =VLOOKUP(A8, Raw_GDP!A8:G19, 5, FALSE) -> 27.3 | F8: =VLOOKUP($A8, Raw_GDP!$A$2:$G$13, 6, FALSE) -> 54.52 | G8: =VLOOKUP($A8, Raw_GDP!$A$2:$G$13, 7, FALSE) -> 9.69 | H8: =VLOOKUP($A8, Raw_Inflation!$A$2:$E$12, 4, FALSE) -> 5.51 | I8: =VLOOKUP($A8, Raw_Inflation!$A$2:$E$12, 5, FALSE) -> 13 | J8: =VLOOKUP($A8, Raw_Unemployment!$A$2:$D$14, 2, FALSE) -> 4.1 | K8: =VLOOKUP($A8, Raw_Unemployment!$A$2:$D$14, 3, FALSE) -> 3.2 | L8: =VLOOKUP($A8, Raw_Unemployment!$A$2:$D$14, 4, FALSE) -> 6.3 | M8: =VLOOKUP($A8, Raw_FDI!$A$2:$E$14, 2, FALSE) -> 84.84 | N8: =VLOOKUP($A8, Raw_FDI!$A$2:$E$14, 3, FALSE) -> 58.77 | O8: =VLOOKUP($A8, Raw_Trade!$A$2:$G$12, 2, FALSE) -> 422 | P8: =VLOOKUP($A8, Raw_Trade!$A$2:$G$12, 3, FALSE) -> 612 | Q8: =VLOOKUP($A8, Raw_Trade!$A$2:$G$12, 4, FALSE) -> -190 | R8: =VLOOKUP($A8, Raw_Trade!$A$2:$G$12, 5, FALSE) -> 254.5 | S8: =VLOOKUP($A8, Raw_Trade!$A$2:$G$12, 6, FALSE) -> 147.4 | T8: =VLOOKUP($A8, Raw_Trade!$A$2:$G$12, 7, FALSE) -> -82.9 | U8: =VLOOKUP($A8, Raw_PerCapita!$A$2:$C$12, 2, FALSE) -> 148524 | V8: =VLOOKUP($A8, Raw_PerCapita!$A$2:$C$12, 3, FALSE) -> 0.169
A9: 2022-23 | B9: =VLOOKUP($A9, Raw_GDP!$A$2:$G$13, 2, FALSE) -> 268.9 | C9: =VLOOKUP($A9, Raw_GDP!$A$2:$G$13, 3, FALSE) -> 161.65 | D9: =VLOOKUP(A9, Raw_GDP!A9:G20, 4, FALSE) -> 18.14 | E9: =VLOOKUP(A9, Raw_GDP!A9:G20, 5, FALSE) -> 26.85 | F9: =VLOOKUP($A9, Raw_GDP!$A$2:$G$13, 6, FALSE) -> 55.01 | G9: =VLOOKUP($A9, Raw_GDP!$A$2:$G$13, 7, FALSE) -> 7 | H9: =VLOOKUP($A9, Raw_Inflation!$A$2:$E$12, 4, FALSE) -> 6.7 | I9: =VLOOKUP($A9, Raw_Inflation!$A$2:$E$12, 5, FALSE) -> 9.45 | J9: =VLOOKUP($A9, Raw_Unemployment!$A$2:$D$14, 2, FALSE) -> 3.2 | K9: =VLOOKUP($A9, Raw_Unemployment!$A$2:$D$14, 3, FALSE) -> 2.4 | L9: =VLOOKUP($A9, Raw_Unemployment!$A$2:$D$14, 4, FALSE) -> 5.4 | M9: =VLOOKUP($A9, Raw_FDI!$A$2:$E$14, 2, FALSE) -> 71.36 | N9: =VLOOKUP($A9, Raw_FDI!$A$2:$E$14, 3, FALSE) -> 46.03 | O9: =VLOOKUP($A9, Raw_Trade!$A$2:$G$12, 2, FALSE) -> 451.1 | P9: =VLOOKUP($A9, Raw_Trade!$A$2:$G$12, 3, FALSE) -> 714.2 | Q9: =VLOOKUP($A9, Raw_Trade!$A$2:$G$12, 4, FALSE) -> -263.1 | R9: =VLOOKUP($A9, Raw_Trade!$A$2:$G$12, 5, FALSE) -> 322.7 | S9: =VLOOKUP($A9, Raw_Trade!$A$2:$G$12, 6, FALSE) -> 158.3 | T9: =VLOOKUP($A9, Raw_Trade!$A$2:$G$12, 7, FALSE) -> -98.7 | U9: =VLOOKUP($A9, Raw_PerCapita!$A$2:$C$12, 2, FALSE) -> 169496 | V9: =VLOOKUP($A9, Raw_PerCapita!$A$2:$C$12, 3, FALSE) -> 0.141
A10: 2023-24 | B10: =VLOOKUP($A10, Raw_GDP!$A$2:$G$13, 2, FALSE) -> 301.23 | C10: =VLOOKUP($A10, Raw_GDP!$A$2:$G$13, 3, FALSE) -> 176.51 | D10: =VLOOKUP(A10, Raw_GDP!A10:G21, 4, FALSE) -> 17.69 | E10: =VLOOKUP(A10, Raw_GDP!A10:G21, 5, FALSE) -> 25.75 | F10: =VLOOKUP($A10, Raw_GDP!$A$2:$G$13, 6, FALSE) -> 56.56 | G10: =VLOOKUP($A10, Raw_GDP!$A$2:$G$13, 7, FALSE) -> 8.2 | H10: =VLOOKUP($A10, Raw_Inflation!$A$2:$E$12, 4, FALSE) -> 5.4 | I10: =VLOOKUP($A10, Raw_Inflation!$A$2:$E$12, 5, FALSE) -> 0.7 | J10: =VLOOKUP($A10, Raw_Unemployment!$A$2:$D$14, 2, FALSE) -> 3.2 | K10: =VLOOKUP($A10, Raw_Unemployment!$A$2:$D$14, 3, FALSE) -> 2.5 | L10: =VLOOKUP($A10, Raw_Unemployment!$A$2:$D$14, 4, FALSE) -> 5.1 | M10: =VLOOKUP($A10, Raw_FDI!$A$2:$E$14, 2, FALSE) -> 71.28 | N10: =VLOOKUP($A10, Raw_FDI!$A$2:$E$14, 3, FALSE) -> 44.42 | O10: =VLOOKUP($A10, Raw_Trade!$A$2:$G$12, 2, FALSE) -> 437.1 | P10: =VLOOKUP($A10, Raw_Trade!$A$2:$G$12, 3, FALSE) -> 678.2 | Q10: =VLOOKUP($A10, Raw_Trade!$A$2:$G$12, 4, FALSE) -> -241.1 | R10: =VLOOKUP($A10, Raw_Trade!$A$2:$G$12, 5, FALSE) -> 341.1 | S10: =VLOOKUP($A10, Raw_Trade!$A$2:$G$12, 6, FALSE) -> 178.3 | T10: =VLOOKUP($A10, Raw_Trade!$A$2:$G$12, 7, FALSE) -> -78.3 | U10: =VLOOKUP($A10, Raw_PerCapita!$A$2:$C$12, 2, FALSE) -> 188892 | V10: =VLOOKUP($A10, Raw_PerCapita!$A$2:$C$12, 3, FALSE) -> 0.114
A11: 2024-25 | B11: =VLOOKUP($A11, Raw_GDP!$A$2:$G$13, 2, FALSE) -> 330.68 | C11: =VLOOKUP($A11, Raw_GDP!$A$2:$G$13, 3, FALSE) -> 187.97 | D11: =VLOOKUP(A11, Raw_GDP!A11:G22, 4, FALSE) -> 17.94 | E11: =VLOOKUP(A11, Raw_GDP!A11:G22, 5, FALSE) -> 27.13 | F11: =VLOOKUP($A11, Raw_GDP!$A$2:$G$13, 6, FALSE) -> 54.93 | G11: =VLOOKUP($A11, Raw_GDP!$A$2:$G$13, 7, FALSE) -> 6.49 | H11: =VLOOKUP($A11, Raw_Inflation!$A$2:$E$12, 4, FALSE) -> 4.6 | I11: =VLOOKUP($A11, Raw_Inflation!$A$2:$E$12, 5, FALSE) -> 2.3 | J11: =VLOOKUP($A11, Raw_Unemployment!$A$2:$D$14, 2, FALSE) -> 4.9 | K11: =VLOOKUP($A11, Raw_Unemployment!$A$2:$D$14, 3, FALSE) -> ~ 4.1 | L11: =VLOOKUP($A11, Raw_Unemployment!$A$2:$D$14, 4, FALSE) -> ~ 6.9 | M11: =VLOOKUP($A11, Raw_FDI!$A$2:$E$14, 2, FALSE) -> 81.04 | N11: =VLOOKUP($A11, Raw_FDI!$A$2:$E$14, 3, FALSE) -> 50.02 | O11: =VLOOKUP($A11, Raw_Trade!$A$2:$G$12, 2, FALSE) -> 437.4 | P11: =VLOOKUP($A11, Raw_Trade!$A$2:$G$12, 3, FALSE) -> 720.2 | Q11: =VLOOKUP($A11, Raw_Trade!$A$2:$G$12, 4, FALSE) -> -282.8 | R11: =VLOOKUP($A11, Raw_Trade!$A$2:$G$12, 5, FALSE) -> 387.5 | S11: =VLOOKUP($A11, Raw_Trade!$A$2:$G$12, 6, FALSE) -> 198.7 | T11: =VLOOKUP($A11, Raw_Trade!$A$2:$G$12, 7, FALSE) -> -94 | U11: =VLOOKUP($A11, Raw_PerCapita!$A$2:$C$12, 2, FALSE) -> 209179 | V11: =VLOOKUP($A11, Raw_PerCapita!$A$2:$C$12, 3, FALSE) -> 0.107

Sheet Calculations
A1: Year | B1: GDP_Current_LakhCr | C1: Real_GDP_Growth_% | D1: GDP_Growth_3Yr_MA_% | E1: CPI_Inflation_% | F1: WPI_Inflation_% | G1: Unemployment_Overall_% | H1: FDI_Total_USD_Bn | I1: Merch_Trade_Balance_USD_Bn | J1: PerCapita_NNI_Rs | K1: PerCapita_Real_Approx | L1: GDP_vs_FDI_Correlation_Helper | M1: GDP vs FDI | N1: Inflation vs Unemployment | O1: GDP growth vs Trade Balance
A2: 2015-16 | B2: =VLOOKUP($A2, Master_Data!$A$2:$V$11, 2, FALSE) -> 135.76 | C2: =VLOOKUP($A2, Master_Data!$A$2:$V$11, 7, FALSE) -> 8 | D2: N/A | E2: =VLOOKUP($A2, Master_Data!$A$2:$V$11, 8, FALSE) -> 4.91 | F2: =VLOOKUP($A2, Master_Data!$A$2:$V$11, 9, FALSE) -> -3.7 | G2: =VLOOKUP($A2, Master_Data!$A$2:$V$11, 10, FALSE) -> 5 | H2: =VLOOKUP($A2, Master_Data!$A$2:$V$11, 13, FALSE) -> 55.56 | I2: =VLOOKUP($A2, Master_Data!$A$2:$V$11, 17, FALSE) -> -119.9 | J2: =VLOOKUP($A2, Master_Data!$A$2:$V$11, 21, FALSE) -> 94797 | K2: =J2 / (E2 / $E$2) -> 94797 | M2: =CORREL(C2:C11, H2:H11) -> -0.36262611 | N2: =CORREL(E2:E11, G2:G11) -> -0.89094876 | O2: =CORREL(C2:C11, I2:I11) -> -0.4009283
A3: 2016-17 | B3: =VLOOKUP($A3, Master_Data!$A$2:$V$11, 2, FALSE) -> 153.92 | C3: =VLOOKUP($A3, Master_Data!$A$2:$V$11, 7, FALSE) -> 8.26 | D3: N/A | E3: =VLOOKUP($A3, Master_Data!$A$2:$V$11, 8, FALSE) -> 4.52 | F3: =VLOOKUP($A3, Master_Data!$A$2:$V$11, 9, FALSE) -> 1.7 | G3: =VLOOKUP($A3, Master_Data!$A$2:$V$11, 10, FALSE) -> 5.4 | H3: =VLOOKUP($A3, Master_Data!$A$2:$V$11, 13, FALSE) -> 60.22 | I3: =VLOOKUP($A3, Master_Data!$A$2:$V$11, 17, FALSE) -> -116.7 | J3: =VLOOKUP($A3, Master_Data!$A$2:$V$11, 21, FALSE) -> 104880 | K3: =J3 / (E3 / $E$2) -> 113929.38 | M3: =CORREL(C3:C12, H3:H12) -> -0.32618385 | N3: =CORREL(E3:E12, G3:G12) -> -0.89530475 | O3: =CORREL(C3:C12, I3:I12) -> -0.4950814
A4: 2017-18 | B4: =VLOOKUP($A4, Master_Data!$A$2:$V$11, 2, FALSE) -> 170.9 | C4: =VLOOKUP($A4, Master_Data!$A$2:$V$11, 7, FALSE) -> 6.8 | D4: =AVERAGE(C2:C4) -> 7.6866667 | E4: =VLOOKUP($A4, Master_Data!$A$2:$V$11, 8, FALSE) -> 3.59 | F4: =VLOOKUP($A4, Master_Data!$A$2:$V$11, 9, FALSE) -> 3 | G4: =VLOOKUP($A4, Master_Data!$A$2:$V$11, 10, FALSE) -> 6.1 | H4: =VLOOKUP($A4, Master_Data!$A$2:$V$11, 13, FALSE) -> 60.97 | I4: =VLOOKUP($A4, Master_Data!$A$2:$V$11, 17, FALSE) -> -162.1 | J4: =VLOOKUP($A4, Master_Data!$A$2:$V$11, 21, FALSE) -> 115293 | K4: =J4 / (E4 / $E$2) -> 157684.86 | M4: =CORREL(C4:C13, H4:H13) -> -0.26257264 | N4: =CORREL(E4:E13, G4:G13) -> -0.8982022 | O4: =CORREL(C4:C13, I4:I13) -> -0.66235508
A5: 2018-19 | B5: =VLOOKUP($A5, Master_Data!$A$2:$V$11, 2, FALSE) -> 188.99 | C5: =VLOOKUP($A5, Master_Data!$A$2:$V$11, 7, FALSE) -> 6.45 | D5: =AVERAGE(C3:C5) -> 7.17 | E5: =VLOOKUP($A5, Master_Data!$A$2:$V$11, 8, FALSE) -> 3.41 | F5: =VLOOKUP($A5, Master_Data!$A$2:$V$11, 9, FALSE) -> 4.3 | G5: =VLOOKUP($A5, Master_Data!$A$2:$V$11, 10, FALSE) -> 5.8 | H5: =VLOOKUP($A5, Master_Data!$A$2:$V$11, 13, FALSE) -> 62 | I5: =VLOOKUP($A5, Master_Data!$A$2:$V$11, 17, FALSE) -> -183.1 | J5: =VLOOKUP($A5, Master_Data!$A$2:$V$11, 21, FALSE) -> 126521 | K5: =J5 / (E5 / $E$2) -> 182175.4 | M5: =CORREL(C5:C14, H5:H14) -> -0.2357148 | N5: =CORREL(E5:E14, G5:G14) -> -0.86289928 | O5: =CORREL(C5:C14, I5:I14) -> -0.71604092
A6: 2019-20 | B6: =VLOOKUP($A6, Master_Data!$A$2:$V$11, 2, FALSE) -> 201.04 | C6: =VLOOKUP($A6, Master_Data!$A$2:$V$11, 7, FALSE) -> 3.87 | D6: =AVERAGE(C4:C6) -> 5.7066667 | E6: =VLOOKUP($A6, Master_Data!$A$2:$V$11, 8, FALSE) -> 4.77 | F6: =VLOOKUP($A6, Master_Data!$A$2:$V$11, 9, FALSE) -> 1.7 | G6: =VLOOKUP($A6, Master_Data!$A$2:$V$11, 10, FALSE) -> 4.8 | H6: =VLOOKUP($A6, Master_Data!$A$2:$V$11, 13, FALSE) -> 74.39 | I6: =VLOOKUP($A6, Master_Data!$A$2:$V$11, 17, FALSE) -> -152.9 | J6: =VLOOKUP($A6, Master_Data!$A$2:$V$11, 21, FALSE) -> 134226 | K6: =J6 / (E6 / $E$2) -> 138165.55 | M6: =CORREL(C6:C15, H6:H15) -> -0.22668549 | N6: =CORREL(E6:E15, G6:G15) -> -0.72158764 | O6: =CORREL(C6:C15, I6:I15) -> -0.7421881
A7: 2020-21 | B7: =VLOOKUP($A7, Master_Data!$A$2:$V$11, 2, FALSE) -> 198.54 | C7: =VLOOKUP($A7, Master_Data!$A$2:$V$11, 7, FALSE) -> -5.78 | D7: =AVERAGE(C5:C7) -> 1.5133333 | E7: =VLOOKUP($A7, Master_Data!$A$2:$V$11, 8, FALSE) -> 6.16 | F7: =VLOOKUP($A7, Master_Data!$A$2:$V$11, 9, FALSE) -> -0.1 | G7: =VLOOKUP($A7, Master_Data!$A$2:$V$11, 10, FALSE) -> 4.2 | H7: =VLOOKUP($A7, Master_Data!$A$2:$V$11, 13, FALSE) -> 81.97 | I7: =VLOOKUP($A7, Master_Data!$A$2:$V$11, 17, FALSE) -> -102.6 | J7: =VLOOKUP($A7, Master_Data!$A$2:$V$11, 21, FALSE) -> 127065 | K7: =J7 / (E7 / $E$2) -> 101280.71 | M7: =CORREL(C7:C16, H7:H16) -> -0.26008327 | N7: =CORREL(E7:E16, G7:G16) -> -0.64225369 | O7: =CORREL(C7:C16, I7:I16) -> -0.76572435
A8: 2021-22 | B8: =VLOOKUP($A8, Master_Data!$A$2:$V$11, 2, FALSE) -> 235.97 | C8: =VLOOKUP($A8, Master_Data!$A$2:$V$11, 7, FALSE) -> 9.69 | D8: =AVERAGE(C6:C8) -> 2.5933333 | E8: =VLOOKUP($A8, Master_Data!$A$2:$V$11, 8, FALSE) -> 5.51 | F8: =VLOOKUP($A8, Master_Data!$A$2:$V$11, 9, FALSE) -> 13 | G8: =VLOOKUP($A8, Master_Data!$A$2:$V$11, 10, FALSE) -> 4.1 | H8: =VLOOKUP($A8, Master_Data!$A$2:$V$11, 13, FALSE) -> 84.84 | I8: =VLOOKUP($A8, Master_Data!$A$2:$V$11, 17, FALSE) -> -190 | J8: =VLOOKUP($A8, Master_Data!$A$2:$V$11, 21, FALSE) -> 148524 | K8: =J8 / (E8 / $E$2) -> 132350.79 | M8: =CORREL(C8:C17, H8:H17) -> 0.3987169 | N8: =CORREL(E8:E17, G8:G17) -> -0.77956717 | O8: =CORREL(C8:C17, I8:I17) -> 0.99202184
A9: 2022-23 | B9: =VLOOKUP($A9, Master_Data!$A$2:$V$11, 2, FALSE) -> 268.9 | C9: =VLOOKUP($A9, Master_Data!$A$2:$V$11, 7, FALSE) -> 7 | D9: =AVERAGE(C7:C9) -> 3.6366667 | E9: =VLOOKUP($A9, Master_Data!$A$2:$V$11, 8, FALSE) -> 6.7 | F9: =VLOOKUP($A9, Master_Data!$A$2:$V$11, 9, FALSE) -> 9.45 | G9: =VLOOKUP($A9, Master_Data!$A$2:$V$11, 10, FALSE) -> 3.2 | H9: =VLOOKUP($A9, Master_Data!$A$2:$V$11, 13, FALSE) -> 71.36 | I9: =VLOOKUP($A9, Master_Data!$A$2:$V$11, 17, FALSE) -> -263.1 | J9: =VLOOKUP($A9, Master_Data!$A$2:$V$11, 21, FALSE) -> 169496 | K9: =J9 / (E9 / $E$2) -> 124212.74 | M9: =CORREL(C9:C18, H9:H18) -> -0.73484748 | N9: =CORREL(E9:E18, G9:G18) -> -0.78986533 | O9: =CORREL(C9:C18, I9:I18) -> 0.9806484
A10: 2023-24 | B10: =VLOOKUP($A10, Master_Data!$A$2:$V$11, 2, FALSE) -> 301.23 | C10: =VLOOKUP($A10, Master_Data!$A$2:$V$11, 7, FALSE) -> 8.2 | D10: =AVERAGE(C8:C10) -> 8.2966667 | E10: =VLOOKUP($A10, Master_Data!$A$2:$V$11, 8, FALSE) -> 5.4 | F10: =VLOOKUP($A10, Master_Data!$A$2:$V$11, 9, FALSE) -> 0.7 | G10: =VLOOKUP($A10, Master_Data!$A$2:$V$11, 10, FALSE) -> 3.2 | H10: =VLOOKUP($A10, Master_Data!$A$2:$V$11, 13, FALSE) -> 71.28 | I10: =VLOOKUP($A10, Master_Data!$A$2:$V$11, 17, FALSE) -> -241.1 | J10: =VLOOKUP($A10, Master_Data!$A$2:$V$11, 21, FALSE) -> 188892 | K10: =J10 / (E10 / $E$2) -> 171751.8 | M10: =CORREL(C10:C19, H10:H19) -> -1 | N10: =CORREL(E10:E19, G10:G19) -> -1 | O10: =CORREL(C10:C19, I10:I19) -> 1
A11: 2024-25 | B11: =VLOOKUP($A11, Master_Data!$A$2:$V$11, 2, FALSE) -> 330.68 | C11: =VLOOKUP($A11, Master_Data!$A$2:$V$11, 7, FALSE) -> 6.49 | D11: =AVERAGE(C9:C11) -> 7.23 | E11: =VLOOKUP($A11, Master_Data!$A$2:$V$11, 8, FALSE) -> 4.6 | F11: =VLOOKUP($A11, Master_Data!$A$2:$V$11, 9, FALSE) -> 2.3 | G11: =VLOOKUP($A11, Master_Data!$A$2:$V$11, 10, FALSE) -> 4.9 | H11: =VLOOKUP($A11, Master_Data!$A$2:$V$11, 13, FALSE) -> 81.04 | I11: =VLOOKUP($A11, Master_Data!$A$2:$V$11, 17, FALSE) -> -282.8 | J11: =VLOOKUP($A11, Master_Data!$A$2:$V$11, 21, FALSE) -> 209179 | K11: =J11 / (E11 / $E$2) -> 223275.85 | M11: =CORREL(C11:C20, H11:H20) -> #DIV/0! | N11: =CORREL(E11:E20, G11:G20) -> #DIV/0! | O11: =CORREL(C11:C20, I11:I20) -> #DIV/0!

Sheet Dashboard
B2: GDP (Current Prices) | E2: CPI Inflation | Z2: LatestYear | AA2: 2024-25
B3: =AA3 -> 330.68 | E3: =AA4 -> 4.6 | Z3: Latest_GDP_Current | AA3: =INDEX(Master_Data!$B$2:$B$11, MATCH($AA$2, Master_Data!$A$2:$A$11, 0)) -> 330.68 | AB3: {=INDEX(Master_Data!$B$2:$B$11, MATCH($AA$2, Master_Data!$A$2:$A$11, 0)-1)} -> 301.23
B4: =(AA3-AB3)/AB3 -> 0.097765827 | C4: YoY change | E4: =(AA4-AB4)/AB4 -> -0.14814815 | F4: YoY change | Z4: Latest_CPI_Infl | AA4: =INDEX(Master_Data!$H$2:$H$11, MATCH($AA$2, Master_Data!$A$2:$A$11, 0)) -> 4.6 | AB4: {=INDEX(Master_Data!H2:H11, MATCH($AA$2, Master_Data!$A$2:$A$11, 0)-1)} -> 5.4
Z5: Latest_Unemp | AA5: =INDEX(Master_Data!$J$2:$J$11, MATCH($AA$2, Master_Data!$A$2:$A$11, 0)) -> 4.9
Z6: Latest_FDI | AA6: =INDEX(Master_Data!$M$2:$M$11, MATCH($AA$2, Master_Data!$A$2:$A$11, 0)) -> 81.04
Z7: Latest_PerCapita | AA7: =INDEX(Master_Data!$U$2:$U$11, MATCH($AA$2, Master_Data!$A$2:$A$11, 0)) -> 209179
